pycosec/__init__.py
pycosec/biometric.py
pycosec-0.1.0.dist-info/licenses/LICENSE
pycosec-0.1.0.dist-info/METADATA
pycosec-0.1.0.dist-info/WHEEL
pycosec-0.1.0.dist-info/top_level.txt
pycosec-0.1.0.dist-info/RECORD
