Metadata-Version: 2.4
Name: pycosec
Version: 0.1.0
Summary: Matrix COSEC biometric Python integration library
Home-page: https://github.com/KSreethul/pycosec
Author: Sreethul Krishna
Author-email: Sreethul Krishna <sreethulkrishna24@gmail.com>
License: LGPL 3.0
Project-URL: Homepage, https://github.com/KSreethul/pycosec
Project-URL: Bug Tracker, https://github.com/KSreethul/pycosec/issues
Keywords: biometric,cosec,attendance,api,pycosec,matrix
Requires-Python: >=3.10
License-File: LICENSE
Requires-Dist: requests>=2.0
Dynamic: author
Dynamic: home-page
Dynamic: license-file
Dynamic: requires-python
